__init__.py
no_long_files.py
flake8_file_length-0.1.0.dist-info/METADATA
flake8_file_length-0.1.0.dist-info/WHEEL
flake8_file_length-0.1.0.dist-info/entry_points.txt
flake8_file_length-0.1.0.dist-info/top_level.txt
flake8_file_length-0.1.0.dist-info/RECORD
