Metadata-Version: 2.4
Name: flake8-file-length
Version: 0.1.0
Summary: Flake8 plugin to enforce a maximum number of lines per file
Author-email: Elie Terrien <contact@elie-terrien.fr>
License-Expression: MIT
Requires-Python: >=3.9
Requires-Dist: flake8>=7.1.1
